scripts/.base_env.sh
scripts/base_build_image.sh
scripts/base_utils.sh
scripts/clean.sh
scripts/pull_images.sh
scripts/push_images.sh
scripts/start_admin.py
scripts/start_predictor.py
scripts/start_worker.py
scripts/stop_all_jobs.py
scripts/docker_swarm/.env.sh
scripts/docker_swarm/build_docs.sh
scripts/docker_swarm/build_images.sh
scripts/docker_swarm/setup_node.sh
scripts/docker_swarm/start.sh
scripts/docker_swarm/stop.sh
scripts/docker_swarm/test/load_db.sh
scripts/docker_swarm/test/start_monitor.sh
scripts/docker_swarm/test/start_predictor_service.sh
scripts/docker_swarm/test/start_rebrow.sh
scripts/docker_swarm/test/start_worker_service.sh
scripts/docker_swarm/test/test.sh
scripts/kubernetes/.env.sh
scripts/kubernetes/build_images.sh
scripts/kubernetes/create_config.py
scripts/kubernetes/create_nfs_pv.sh
scripts/kubernetes/create_nfs_pvc.sh
scripts/kubernetes/generate_config.sh
scripts/kubernetes/remove_config.sh
scripts/kubernetes/start.sh
scripts/kubernetes/start_monitor.sh
scripts/kubernetes/start_stolon.sh
scripts/kubernetes/stop.sh
scripts/kubernetes/stop_stolon.sh
scripts/kubernetes/cluster_check/replace_services.sh
scripts/kubernetes/cluster_check/show_cluster_status.sh
scripts/kubernetes/cluster_check/update_services.sh
scripts/kubernetes/stolon/generate_stolon_yaml.sh
scripts/kubernetes/stolon/secret.yaml.template
scripts/kubernetes/stolon/stolon-keeper.yaml.template
scripts/kubernetes/stolon/stolon-proxy-service.yaml.template
scripts/kubernetes/stolon/stolon-proxy.yaml.template
scripts/kubernetes/stolon/stolon-sentinel.yaml.template
scripts/kubernetes/test/load_db.sh
scripts/kubernetes/test/test_gpu.json
scripts/kubernetes/yaml/dns-horizontal-autoscaler.yaml
scripts/kubernetes/yaml/ingress_controller_deploy.yaml
scripts/kubernetes/yaml/nfs-pv.yaml.template
scripts/kubernetes/yaml/nfs-pvc.yaml.template
scripts/kubernetes/yaml/nvidia-device-plugin.yml
scripts/kubernetes/yaml/spark-rbac.yaml
singa_auto/__init__.py
singa_auto/__init__.pyc
singa_auto-0.3.4.dist-info/LICENSE
singa_auto-0.3.4.dist-info/METADATA
singa_auto-0.3.4.dist-info/WHEEL
singa_auto-0.3.4.dist-info/entry_points.txt
singa_auto-0.3.4.dist-info/top_level.txt
singa_auto-0.3.4.dist-info/RECORD
